pyazureutils/__init__.py
pyazureutils/cli_iotcentral.py
pyazureutils/cli_pyazureutils.py
pyazureutils/iotcentral.py
pyazureutils/logfilters.py
pyazureutils/logging.yaml
pyazureutils/pyazureutils_errors.py
pyazureutils/status_codes.py
pyazureutils-1.1.4.9.dist-info/LICENSE.txt
pyazureutils-1.1.4.9.dist-info/METADATA
pyazureutils-1.1.4.9.dist-info/WHEEL
pyazureutils-1.1.4.9.dist-info/entry_points.txt
pyazureutils-1.1.4.9.dist-info/top_level.txt
pyazureutils-1.1.4.9.dist-info/RECORD
